[
    {
        "points": [
            [
                39,
                25
            ],
            [
                176,
                174
            ],
            [
                483,
                178
            ],
            [
                601,
                28
            ]
        ],
        "rgb": [
            88,
            77,
            86
        ]
    },
    {
        "points": [
            [
                16,
                36
            ],
            [
                157,
                190
            ],
            [
                157,
                351
            ],
            [
                17,
                467
            ]
        ],
        "rgb": [
            60,
            110,
            113
        ]
    },
    {
        "points": [
            [
                55,
                466
            ],
            [
                148,
                381
            ],
            [
                456,
                374
            ],
            [
                574,
                465
            ]
        ],
        "rgb": [
            190,
            238,
            98
        ]
    },
    {
        "points": [
            [
                619,
                35
            ],
            [
                499,
                190
            ],
            [
                470,
                363
            ],
            [
                612,
                456
            ]
        ],
        "rgb": [
            244,
            116,
            59
        ]
    }
]